ot_analysis/__init__.py
ot_analysis/__main__.py
ot_analysis/setup_logger.py
ot_analysis/controller/__init__.py
ot_analysis/controller/controller.py
ot_analysis/extractor/__init__.py
ot_analysis/extractor/jpk_extractor.py
ot_analysis/model/__init__.py
ot_analysis/model/curve.py
ot_analysis/model/optical_effect.py
ot_analysis/model/segment_curve.py
ot_analysis/view/__init__.py
ot_analysis/view/graph_view.py
ot_analysis/view/info.py
ot_analysis/view/mainview.py
ot_analysis/view/toggle.py
OT_Analysis-0.1.3.dist-info/LICENSE
OT_Analysis-0.1.3.dist-info/METADATA
OT_Analysis-0.1.3.dist-info/WHEEL
OT_Analysis-0.1.3.dist-info/entry_points.txt
OT_Analysis-0.1.3.dist-info/top_level.txt
OT_Analysis-0.1.3.dist-info/RECORD
