Metadata-Version: 2.1
Name: OT-Analysis
Version: 0.1.3
Summary: Tools for extracting, analyzing and classifying optical tweezer data curves
Home-page: https://github.com/phpuech/OT_Analysis.git
Author: Thierry GALLIANO (LAI)
Author-email: thierry.galliano@etu.univ-amu.fr
License: GPL-3.0-only
Classifier: Intended Audience :: Developers
Classifier: Programming Language :: Python :: 3.9
Classifier: License :: OSI Approved :: GNU General Public License v3 (GPLv3)
Classifier: Operating System :: OS Independent
Requires-Python: >=3.7
License-File: LICENSE
Requires-Dist: numpy (>=1.21)
Requires-Dist: pandas
Requires-Dist: scipy
Requires-Dist: matplotlib
Requires-Dist: PyQt5
Requires-Dist: supyr-struct
Requires-Dist: pathlib
Requires-Dist: art
Provides-Extra: dev
Requires-Dist: pytest ; extra == 'dev'
Requires-Dist: pytest-cov ; extra == 'dev'
Requires-Dist: sphinx ; extra == 'dev'
Requires-Dist: sphinx-rtd-theme ; extra == 'dev'
Requires-Dist: m2r2 ; extra == 'dev'
